dask_distance
